{"ShortInfo":{"Id":"124931","ImageUrl":"http://resources.wimpmusic.com/images/f42403db/4ce6/4047/a96b/9b6c6198731d/160x160.jpg","Url":"https://play.wimpmusic.com/album/124931","Name":"Powerslave","Artist":"Iron Maiden"},"Tracks":[{"TrackNumber":1,"Name":"Aces High (1998 Remastered Version)","Artist":"Iron Maiden","Album":null,"Url":null,"Time":"4:29"},{"TrackNumber":2,"Name":"2 Minutes To Midnight (1998 Remastered Version)","Artist":"Iron Maiden","Album":null,"Url":null,"Time":"5:59"},{"TrackNumber":3,"Name":"Losfer Words (Big 'Orra) (1998 Remastered Version)","Artist":"Iron Maiden","Album":null,"Url":null,"Time":"4:12"},{"TrackNumber":4,"Name":"Flash Of The Blade (1998 Remastered Version)","Artist":"Iron Maiden","Album":null,"Url":null,"Time":"4:02"},{"TrackNumber":5,"Name":"The Duelists (1998 Remastered Version)","Artist":"Iron Maiden","Album":null,"Url":null,"Time":"6:06"},{"TrackNumber":6,"Name":"Back In The Village (1998 Remastered Version)","Artist":"Iron Maiden","Album":null,"Url":null,"Time":"5:20"},{"TrackNumber":7,"Name":"Powerslave (1998 Remastered Version)","Artist":"Iron Maiden","Album":null,"Url":null,"Time":"6:47"},{"TrackNumber":8,"Name":"Rime Of The Ancient Mariner (1998 Remastered Version)","Artist":"Iron Maiden","Album":null,"Url":null,"Time":"13:34"}],"Name":"Powerslave","Artist":"Iron Maiden","Year":"1984","TotalLength":"51:37","Copyright":"1998 Iron Maiden Holdings Ltd. This label copy information is the subject of copyright protection. All rights reserved. (C) 1998 Parlophone Records Ltd","MediumImageUri":"http://resources.wimpmusic.com/images/f42403db/4ce6/4047/a96b/9b6c6198731d/320x320.jpg","LargeImageUri":"http://resources.wimpmusic.com/images/f42403db/4ce6/4047/a96b/9b6c6198731d/1280x1280.jpg"}