{"ShortInfo":{"Id":"1270702","ImageUrl":"http://resources.wimpmusic.com/images/7d25ebad/ed8c/4580/8cb3/59862be498d6/160x160.jpg","Url":"https://play.wimpmusic.com/album/1270702","Name":"Out Of This World","Artist":"Europe"},"Tracks":[{"TrackNumber":1,"Name":"Superstitious","Artist":"Europe","Album":null,"Url":null,"Time":"4:34"},{"TrackNumber":2,"Name":"Let the Good Times Rock","Artist":"Europe","Album":null,"Url":null,"Time":"4:04"},{"TrackNumber":3,"Name":"Open Your Heart","Artist":"Europe","Album":null,"Url":null,"Time":"4:04"},{"TrackNumber":4,"Name":"More Than Meets the Eye","Artist":"Europe","Album":null,"Url":null,"Time":"3:20"},{"TrackNumber":5,"Name":"Coast to Coast","Artist":"Europe","Album":null,"Url":null,"Time":"4:01"},{"TrackNumber":6,"Name":"Ready or Not","Artist":"Europe","Album":null,"Url":null,"Time":"4:05"},{"TrackNumber":7,"Name":"Sign of the Times","Artist":"Europe","Album":null,"Url":null,"Time":"4:15"},{"TrackNumber":8,"Name":"Just the Beginning","Artist":"Europe","Album":null,"Url":null,"Time":"4:32"},{"TrackNumber":9,"Name":"Never Say Die","Artist":"Europe","Album":null,"Url":null,"Time":"4:00"},{"TrackNumber":10,"Name":"Lights and Shadows","Artist":"Europe","Album":null,"Url":null,"Time":"4:04"},{"TrackNumber":11,"Name":"Tower's Callin'","Artist":"Europe","Album":null,"Url":null,"Time":"3:48"},{"TrackNumber":12,"Name":"Tomorrow","Artist":"Europe","Album":null,"Url":null,"Time":"3:04"}],"Name":"Out Of This World","Artist":"Europe","Year":"1988","TotalLength":"47:51","Copyright":"(P) 1988 Sony Music Entertainment Inc.","MediumImageUri":"http://resources.wimpmusic.com/images/7d25ebad/ed8c/4580/8cb3/59862be498d6/320x320.jpg","LargeImageUri":"http://resources.wimpmusic.com/images/7d25ebad/ed8c/4580/8cb3/59862be498d6/1280x1280.jpg"}