{"ShortInfo":{"Id":"14234183","ImageUrl":"http://resources.wimpmusic.com/images/ad54890b/8e3e/445f/a9cb/8c2181984448/160x160.jpg","Url":"https://play.wimpmusic.com/album/14234183","Name":"Nashville Skyline","Artist":"Bob Dylan"},"Tracks":[{"TrackNumber":1,"Name":"Girl from the North Country","Artist":"Bob Dylan","Album":null,"Url":null,"Time":"3:41"},{"TrackNumber":2,"Name":"Nashville Skyline Rag","Artist":"Bob Dylan","Album":null,"Url":null,"Time":"3:11"},{"TrackNumber":3,"Name":"To Be Alone with You","Artist":"Bob Dylan","Album":null,"Url":null,"Time":"2:08"},{"TrackNumber":4,"Name":"I Threw It All Away","Artist":"Bob Dylan","Album":null,"Url":null,"Time":"2:23"},{"TrackNumber":5,"Name":"Peggy Day","Artist":"Bob Dylan","Album":null,"Url":null,"Time":"2:00"},{"TrackNumber":6,"Name":"Lay, Lady, Lay","Artist":"Bob Dylan","Album":null,"Url":null,"Time":"3:18"},{"TrackNumber":7,"Name":"One More Night","Artist":"Bob Dylan","Album":null,"Url":null,"Time":"2:22"},{"TrackNumber":8,"Name":"Tell Me That It Isn't True","Artist":"Bob Dylan","Album":null,"Url":null,"Time":"2:40"},{"TrackNumber":9,"Name":"Country Pie","Artist":"Bob Dylan","Album":null,"Url":null,"Time":"1:37"},{"TrackNumber":10,"Name":"Tonight I'll Be Staying Here with You","Artist":"Bob Dylan","Album":null,"Url":null,"Time":"3:22"}],"Name":"Nashville Skyline","Artist":"Bob Dylan","Year":"1988","TotalLength":"26:42","Copyright":"Originally released 1969 SONY BMG MUSIC ENTERTAINMENT","MediumImageUri":"http://resources.wimpmusic.com/images/ad54890b/8e3e/445f/a9cb/8c2181984448/320x320.jpg","LargeImageUri":"http://resources.wimpmusic.com/images/ad54890b/8e3e/445f/a9cb/8c2181984448/1280x1280.jpg"}