{"ShortInfo":{"Id":"14297761","ImageUrl":"http://resources.wimpmusic.com/images/f2553a17/1f93/47b6/a587/a63b6dd88eaf/160x160.jpg","Url":"https://play.wimpmusic.com/album/14297761","Name":"Another Side Of Bob Dylan","Artist":"Bob Dylan"},"Tracks":[{"TrackNumber":1,"Name":"All I Really Want to Do","Artist":"Bob Dylan","Album":null,"Url":null,"Time":"4:05"},{"TrackNumber":2,"Name":"Black Crow Blues","Artist":"Bob Dylan","Album":null,"Url":null,"Time":"3:14"},{"TrackNumber":3,"Name":"Spanish Harlem Incident","Artist":"Bob Dylan","Album":null,"Url":null,"Time":"2:25"},{"TrackNumber":4,"Name":"Chimes of Freedom","Artist":"Bob Dylan","Album":null,"Url":null,"Time":"7:09"},{"TrackNumber":5,"Name":"I Shall Be Free No. 10","Artist":"Bob Dylan","Album":null,"Url":null,"Time":"4:48"},{"TrackNumber":6,"Name":"To Ramona","Artist":"Bob Dylan","Album":null,"Url":null,"Time":"3:51"},{"TrackNumber":7,"Name":"Motorpsycho Nightmare","Artist":"Bob Dylan","Album":null,"Url":null,"Time":"4:32"},{"TrackNumber":8,"Name":"My Back Pages","Artist":"Bob Dylan","Album":null,"Url":null,"Time":"4:22"},{"TrackNumber":9,"Name":"I Don't Believe You (She Acts Like We Never Have Met)","Artist":"Bob Dylan","Album":null,"Url":null,"Time":"4:22"},{"TrackNumber":10,"Name":"Ballad in Plain D","Artist":"Bob Dylan","Album":null,"Url":null,"Time":"8:16"},{"TrackNumber":11,"Name":"It Ain't Me Babe","Artist":"Bob Dylan","Album":null,"Url":null,"Time":"3:33"}],"Name":"Another Side Of Bob Dylan","Artist":"Bob Dylan","Year":"1989","TotalLength":"50:30","Copyright":"Originally Released 1964 Sony Music Entertainment Inc.","MediumImageUri":"http://resources.wimpmusic.com/images/f2553a17/1f93/47b6/a587/a63b6dd88eaf/320x320.jpg","LargeImageUri":"http://resources.wimpmusic.com/images/f2553a17/1f93/47b6/a587/a63b6dd88eaf/1280x1280.jpg"}