{"ShortInfo":{"Id":"153573","ImageUrl":"http://resources.wimpmusic.com/images/88983ba5/47b5/4d05/81c3/ea801cbfe2d2/160x160.jpg","Url":"https://play.wimpmusic.com/album/153573","Name":"Concerto For Group And Orchestra","Artist":"Deep Purple"},"Tracks":[{"TrackNumber":1,"Name":"Intro (Music and Spoken Word)","Artist":"Deep Purple","Album":null,"Url":null,"Time":"3:27"},{"TrackNumber":2,"Name":"Hush (Live)","Artist":"Deep Purple","Album":null,"Url":null,"Time":"4:40"},{"TrackNumber":3,"Name":"Wring That Neck (Live)","Artist":"Deep Purple","Album":null,"Url":null,"Time":"13:23"},{"TrackNumber":4,"Name":"Child in Time (Live)","Artist":"Deep Purple","Album":null,"Url":null,"Time":"12:02"}],"Name":"Concerto For Group And Orchestra","Artist":"Deep Purple","Year":"2002","TotalLength":"1:31:04","Copyright":"2002 Deep Purple (Overseas) Ltd. This label copy information is the subject of copyright protection. All rights reserved. (C) 2002 Parlophone Records Ltd","MediumImageUri":"http://resources.wimpmusic.com/images/88983ba5/47b5/4d05/81c3/ea801cbfe2d2/320x320.jpg","LargeImageUri":"http://resources.wimpmusic.com/images/88983ba5/47b5/4d05/81c3/ea801cbfe2d2/1280x1280.jpg"}