{"ShortInfo":{"Id":"1879516","ImageUrl":"http://resources.wimpmusic.com/images/cba463e2/1887/4545/a2ca/31b3bff32d66/160x160.jpg","Url":"https://play.wimpmusic.com/album/1879516","Name":"13 Chansons Nouvelles","Artist":"Joe Dassin"},"Tracks":[{"TrackNumber":1,"Name":"À chacun sa chanson (Live à  l'Olympia)","Artist":"Joe Dassin","Album":null,"Url":null,"Time":"3:10"},{"TrackNumber":2,"Name":"On s'en va","Artist":"Joe Dassin","Album":null,"Url":null,"Time":"2:48"},{"TrackNumber":3,"Name":"Dédé le kid","Artist":"Joe Dassin","Album":null,"Url":null,"Time":"2:37"},{"TrackNumber":4,"Name":"Pourquoi pas moi","Artist":"Joe Dassin","Album":null,"Url":null,"Time":"3:44"},{"TrackNumber":5,"Name":"Allons danser Valérie","Artist":"Joe Dassin","Album":null,"Url":null,"Time":"2:44"},{"TrackNumber":6,"Name":"Les plus belles années de ma vie (The Best Years of My Life)","Artist":"Joe Dassin","Album":null,"Url":null,"Time":"4:39"},{"TrackNumber":7,"Name":"La dernière page","Artist":"Joe Dassin","Album":null,"Url":null,"Time":"2:18"},{"TrackNumber":8,"Name":"Qu'est-ce que j'ai pu faire hier soir?","Artist":"Joe Dassin","Album":null,"Url":null,"Time":"2:25"},{"TrackNumber":9,"Name":"Quand on a seize ans (Live à  l'Olympia)","Artist":"Joe Dassin","Album":null,"Url":null,"Time":"2:28"},{"TrackNumber":10,"Name":"Oh la la!","Artist":"Joe Dassin","Album":null,"Url":null,"Time":"2:50"},{"TrackNumber":11,"Name":"Ton côté du lit","Artist":"Joe Dassin","Album":null,"Url":null,"Time":"3:21"},{"TrackNumber":12,"Name":"Quand on a du feu","Artist":"Joe Dassin","Album":null,"Url":null,"Time":"2:40"},{"TrackNumber":13,"Name":"Fais-moi de l'electricité","Artist":"Joe Dassin","Album":null,"Url":null,"Time":"2:26"}],"Name":"13 Chansons Nouvelles","Artist":"Joe Dassin","Year":"1995","TotalLength":"38:05","Copyright":"Compilation (P) 1973 Sony Music Entertainment (France) S.A.","MediumImageUri":"http://resources.wimpmusic.com/images/cba463e2/1887/4545/a2ca/31b3bff32d66/320x320.jpg","LargeImageUri":"http://resources.wimpmusic.com/images/cba463e2/1887/4545/a2ca/31b3bff32d66/1280x1280.jpg"}