{"ShortInfo":{"Id":"20481663","ImageUrl":"http://resources.wimpmusic.com/images/3cc7381b/ad19/4067/8067/e87b181a2202/160x160.jpg","Url":"https://play.wimpmusic.com/album/20481663","Name":"The Official Deep Purple (Overseas) Live Series: Copenhagen 1972","Artist":"Deep Purple"},"Tracks":[{"TrackNumber":1,"Name":"Highway Star (Live in Copenhagen 1972)","Artist":"Deep Purple","Album":null,"Url":null,"Time":"8:25"},{"TrackNumber":2,"Name":"Strange Kind of Woman (Live in Copenhagen 1972)","Artist":"Deep Purple","Album":null,"Url":null,"Time":"9:33"},{"TrackNumber":3,"Name":"Child in Time (Live in Copenhagen 1972)","Artist":"Deep Purple","Album":null,"Url":null,"Time":"17:26"},{"TrackNumber":4,"Name":"The Mule (Live in Copenhagen 1972)","Artist":"Deep Purple","Album":null,"Url":null,"Time":"9:23"},{"TrackNumber":5,"Name":"Lazy (Live in Copenhagen 1972)","Artist":"Deep Purple","Album":null,"Url":null,"Time":"11:16"},{"TrackNumber":6,"Name":"Space Truckin' (Live in Copenhagen 1972)","Artist":"Deep Purple","Album":null,"Url":null,"Time":"22:10"},{"TrackNumber":7,"Name":"Fireball (Live in Copenhagen 1972)","Artist":"Deep Purple","Album":null,"Url":null,"Time":"5:11"},{"TrackNumber":8,"Name":"Lucille (Live in Copenhagen 1972)","Artist":"Deep Purple","Album":null,"Url":null,"Time":"5:55"},{"TrackNumber":9,"Name":"Black Night (Live in Copenhagen 1972)","Artist":"Deep Purple","Album":null,"Url":null,"Time":"6:14"},{"TrackNumber":10,"Name":"Strange Kind of Woman (Live in New York 1973)","Artist":"Deep Purple","Album":null,"Url":null,"Time":"6:16"},{"TrackNumber":11,"Name":"Smoke on the Water (Live in New York 1973)","Artist":"Deep Purple","Album":null,"Url":null,"Time":"5:22"},{"TrackNumber":12,"Name":"Space Truckin' (Live in New York 1973)","Artist":"Deep Purple","Album":null,"Url":null,"Time":"10:39"},{"TrackNumber":13,"Name":"1971 Australian Interview","Artist":"Deep Purple","Album":null,"Url":null,"Time":"5:44"}],"Name":"The Official Deep Purple (Overseas) Live Series: Copenhagen 1972","Artist":"Deep Purple","Year":"2013","TotalLength":"2:03:34","Copyright":"2013 Edel Germany GmbH. earMUSIC is a project of Edel.","MediumImageUri":"http://resources.wimpmusic.com/images/3cc7381b/ad19/4067/8067/e87b181a2202/320x320.jpg","LargeImageUri":"http://resources.wimpmusic.com/images/3cc7381b/ad19/4067/8067/e87b181a2202/1280x1280.jpg"}