{"ShortInfo":{"Id":"29582940","ImageUrl":"http://resources.wimpmusic.com/images/8a3f7c58/756c/4a2a/8979/f2d60a9948dd/160x160.jpg","Url":"https://play.wimpmusic.com/album/29582940","Name":"Grave Disorder","Artist":"The Damned"},"Tracks":[{"TrackNumber":1,"Name":"Democracy?","Artist":"The Damned","Album":null,"Url":null,"Time":"3:22"},{"TrackNumber":2,"Name":"Song.com","Artist":"The Damned","Album":null,"Url":null,"Time":"3:40"},{"TrackNumber":3,"Name":"Thrill Kill","Artist":"The Damned","Album":null,"Url":null,"Time":"5:38"},{"TrackNumber":4,"Name":"She","Artist":"The Damned","Album":null,"Url":null,"Time":"4:28"},{"TrackNumber":5,"Name":"Lookin For Action","Artist":"The Damned","Album":null,"Url":null,"Time":"4:04"},{"TrackNumber":6,"Name":"Would You Be So Hot (If You Weren't Dead?)","Artist":"The Damned","Album":null,"Url":null,"Time":"4:14"},{"TrackNumber":7,"Name":"Absinthe","Artist":"The Damned","Album":null,"Url":null,"Time":"4:19"},{"TrackNumber":8,"Name":"Amen","Artist":"The Damned","Album":null,"Url":null,"Time":"7:55"},{"TrackNumber":9,"Name":"Neverland","Artist":"The Damned","Album":null,"Url":null,"Time":"3:31"},{"TrackNumber":10,"Name":"'Til The End Of Time","Artist":"The Damned","Album":null,"Url":null,"Time":"3:53"},{"TrackNumber":11,"Name":"Obscene","Artist":"The Damned","Album":null,"Url":null,"Time":"2:47"},{"TrackNumber":12,"Name":"W","Artist":"The Damned","Album":null,"Url":null,"Time":"5:06"},{"TrackNumber":13,"Name":"Beauty Of The Beast","Artist":"The Damned","Album":null,"Url":null,"Time":"4:44"}],"Name":"Grave Disorder","Artist":"The Damned","Year":"2001","TotalLength":"57:41","Copyright":"© 2001 Nitro Records","MediumImageUri":"http://resources.wimpmusic.com/images/8a3f7c58/756c/4a2a/8979/f2d60a9948dd/320x320.jpg","LargeImageUri":"http://resources.wimpmusic.com/images/8a3f7c58/756c/4a2a/8979/f2d60a9948dd/1280x1280.jpg"}