{"ShortInfo":{"Id":"34535370","ImageUrl":"http://resources.wimpmusic.com/images/a649eaf1/910c/4021/9e27/433a26f94fe1/160x160.jpg","Url":"https://play.wimpmusic.com/album/34535370","Name":"Split","Artist":"Good Riddance"},"Tracks":[{"TrackNumber":1,"Name":"Judas And The Morning After Pill","Artist":"Good Riddance","Album":null,"Url":null,"Time":"1:27"},{"TrackNumber":2,"Name":"Grandstanding From The Cheap Seats","Artist":"Good Riddance","Album":null,"Url":null,"Time":"1:25"},{"TrackNumber":3,"Name":"Queen &amp; John","Artist":"Good Riddance","Album":null,"Url":null,"Time":"2:07"},{"TrackNumber":4,"Name":"Strickland Vs. Washington","Artist":"Good Riddance","Album":null,"Url":null,"Time":"1:13"},{"TrackNumber":5,"Name":"Chesterfield King And Propagandhi","Artist":"Kill Your Idols","Album":null,"Url":null,"Time":"1:33"},{"TrackNumber":6,"Name":"I Told You So","Artist":"Kill Your Idols","Album":null,"Url":null,"Time":"2:35"},{"TrackNumber":7,"Name":"Another Start To A Miserable Day","Artist":"Kill Your Idols","Album":null,"Url":null,"Time":"2:53"}],"Name":"Split","Artist":"Good Riddance","Year":"2001","TotalLength":"13:13","Copyright":"2016 Epitaph","MediumImageUri":"http://resources.wimpmusic.com/images/a649eaf1/910c/4021/9e27/433a26f94fe1/320x320.jpg","LargeImageUri":"http://resources.wimpmusic.com/images/a649eaf1/910c/4021/9e27/433a26f94fe1/1280x1280.jpg"}