{"ShortInfo":{"Id":"35703577","ImageUrl":"http://resources.wimpmusic.com/images/cfd72d5b/49e3/49d9/9877/73541e7fad16/160x160.jpg","Url":"https://play.wimpmusic.com/album/35703577","Name":"Crash Love (Deluxe)","Artist":"AFI"},"Tracks":[{"TrackNumber":1,"Name":"Torch Song","Artist":"AFI","Album":null,"Url":null,"Time":"3:45"},{"TrackNumber":2,"Name":"Beautiful Thieves","Artist":"AFI","Album":null,"Url":null,"Time":"3:46"},{"TrackNumber":3,"Name":"End Transmission","Artist":"AFI","Album":null,"Url":null,"Time":"3:46"},{"TrackNumber":4,"Name":"Too Shy To Scream","Artist":"AFI","Album":null,"Url":null,"Time":"2:57"},{"TrackNumber":5,"Name":"Veronica Sawyer Smokes","Artist":"AFI","Album":null,"Url":null,"Time":"2:44"},{"TrackNumber":6,"Name":"Okay, I Feel Better Now","Artist":"AFI","Album":null,"Url":null,"Time":"4:31"},{"TrackNumber":7,"Name":"Medicate","Artist":"AFI","Album":null,"Url":null,"Time":"4:21"},{"TrackNumber":8,"Name":"I Am Trying Very Hard To Be Here","Artist":"AFI","Album":null,"Url":null,"Time":"2:44"},{"TrackNumber":9,"Name":"Sacrilege","Artist":"AFI","Album":null,"Url":null,"Time":"3:27"},{"TrackNumber":10,"Name":"Darling, I Want To Destroy You","Artist":"AFI","Album":null,"Url":null,"Time":"3:43"},{"TrackNumber":11,"Name":"Cold Hands","Artist":"AFI","Album":null,"Url":null,"Time":"3:32"},{"TrackNumber":12,"Name":"It Was Mine","Artist":"AFI","Album":null,"Url":null,"Time":"3:54"}],"Name":"Crash Love (Deluxe)","Artist":"AFI","Year":"2009","TotalLength":"1:00:10","Copyright":"© 2009 DGC Records","MediumImageUri":"http://resources.wimpmusic.com/images/cfd72d5b/49e3/49d9/9877/73541e7fad16/320x320.jpg","LargeImageUri":"http://resources.wimpmusic.com/images/cfd72d5b/49e3/49d9/9877/73541e7fad16/1280x1280.jpg"}