{"ShortInfo":{"Id":"3962278","ImageUrl":"http://resources.wimpmusic.com/images/eaac4dd4/2fbd/4b99/a0ae/7b1fce03b436/160x160.jpg","Url":"https://play.wimpmusic.com/album/3962278","Name":"CexCells","Artist":"Blaqk Audio"},"Tracks":[{"TrackNumber":1,"Name":"Stiff Kittens","Artist":"Blaqk Audio","Album":null,"Url":null,"Time":"3:46"},{"TrackNumber":2,"Name":"Between Breaths (An XX Perspective)","Artist":"Blaqk Audio","Album":null,"Url":null,"Time":"4:27"},{"TrackNumber":3,"Name":"Snuff On Digital","Artist":"Blaqk Audio","Album":null,"Url":null,"Time":"5:02"},{"TrackNumber":4,"Name":"Bitter For Sweet","Artist":"Blaqk Audio","Album":null,"Url":null,"Time":"6:10"},{"TrackNumber":5,"Name":"Where Would You Like Them Left?","Artist":"Blaqk Audio","Album":null,"Url":null,"Time":"4:16"},{"TrackNumber":6,"Name":"The Fear Of Being Found","Artist":"Blaqk Audio","Album":null,"Url":null,"Time":"4:43"},{"TrackNumber":7,"Name":"On A Friday","Artist":"Blaqk Audio","Album":null,"Url":null,"Time":"4:13"},{"TrackNumber":8,"Name":"The Love Letter","Artist":"Blaqk Audio","Album":null,"Url":null,"Time":"4:21"},{"TrackNumber":9,"Name":"Semiotic Love","Artist":"Blaqk Audio","Album":null,"Url":null,"Time":"3:31"},{"TrackNumber":10,"Name":"Cities Of Night","Artist":"Blaqk Audio","Album":null,"Url":null,"Time":"3:46"},{"TrackNumber":11,"Name":"Again, Again And Again","Artist":"Blaqk Audio","Album":null,"Url":null,"Time":"3:24"},{"TrackNumber":12,"Name":"Wake Up, Open The Door And Escape To The Sea","Artist":"Blaqk Audio","Album":null,"Url":null,"Time":"3:05"},{"TrackNumber":13,"Name":"Black Electric","Artist":"Blaqk Audio","Album":null,"Url":null,"Time":"3:12"}],"Name":"CexCells","Artist":"Blaqk Audio","Year":"2007","TotalLength":"53:58","Copyright":"© 2007 Interscope Records","MediumImageUri":"http://resources.wimpmusic.com/images/eaac4dd4/2fbd/4b99/a0ae/7b1fce03b436/320x320.jpg","LargeImageUri":"http://resources.wimpmusic.com/images/eaac4dd4/2fbd/4b99/a0ae/7b1fce03b436/1280x1280.jpg"}