{"ShortInfo":{"Id":"43744612","ImageUrl":"http://resources.wimpmusic.com/images/774e064e/883e/4db6/bc29/8ea54e9521d9/160x160.jpg","Url":"https://play.wimpmusic.com/album/43744612","Name":"Sex, Love And Rock 'N' Roll","Artist":"Social Distortion"},"Tracks":[{"TrackNumber":1,"Name":"Reach For The Sky","Artist":"Social Distortion","Album":null,"Url":null,"Time":"3:32"},{"TrackNumber":2,"Name":"Highway 101","Artist":"Social Distortion","Album":null,"Url":null,"Time":"3:45"},{"TrackNumber":3,"Name":"Don't Take Me For Granted","Artist":"Social Distortion","Album":null,"Url":null,"Time":"3:48"},{"TrackNumber":4,"Name":"Footprints On My Ceiling","Artist":"Social Distortion","Album":null,"Url":null,"Time":"5:09"},{"TrackNumber":5,"Name":"Nickels And Dimes","Artist":"Social Distortion","Album":null,"Url":null,"Time":"3:05"},{"TrackNumber":6,"Name":"I Wasn't Born To Follow","Artist":"Social Distortion","Album":null,"Url":null,"Time":"2:56"},{"TrackNumber":7,"Name":"Winner And Losers","Artist":"Social Distortion","Album":null,"Url":null,"Time":"4:45"},{"TrackNumber":8,"Name":"Faithless","Artist":"Social Distortion","Album":null,"Url":null,"Time":"3:02"},{"TrackNumber":9,"Name":"Live Before You Die","Artist":"Social Distortion","Album":null,"Url":null,"Time":"2:48"},{"TrackNumber":10,"Name":"Angel's Wings","Artist":"Social Distortion","Album":null,"Url":null,"Time":"4:59"}],"Name":"Sex, Love And Rock 'N' Roll","Artist":"Social Distortion","Year":"2004","TotalLength":"37:43","Copyright":"© 2004 The Bicycle Music Company","MediumImageUri":"http://resources.wimpmusic.com/images/774e064e/883e/4db6/bc29/8ea54e9521d9/320x320.jpg","LargeImageUri":"http://resources.wimpmusic.com/images/774e064e/883e/4db6/bc29/8ea54e9521d9/1280x1280.jpg"}