{"ShortInfo":{"Id":"59251377","ImageUrl":"http://resources.wimpmusic.com/images/2d9e5d56/477c/4b0a/a002/9aaf3b103581/160x160.jpg","Url":"https://play.wimpmusic.com/album/59251377","Name":"How It Works Bonus","Artist":"Bodyjar"},"Tracks":[{"TrackNumber":1,"Name":"Halfway Around The World","Artist":"Bodyjar","Album":null,"Url":null,"Time":"3:28"},{"TrackNumber":2,"Name":"Self Inflicted","Artist":"Bodyjar","Album":null,"Url":null,"Time":"2:42"},{"TrackNumber":3,"Name":"Not Alive","Artist":"Bodyjar","Album":null,"Url":null,"Time":"3:10"},{"TrackNumber":4,"Name":"Fall into Place","Artist":"Bodyjar","Album":null,"Url":null,"Time":"2:56"},{"TrackNumber":5,"Name":"Coolidge","Artist":"Bodyjar","Album":null,"Url":null,"Time":"2:42"},{"TrackNumber":6,"Name":"Hazy Shade of Winter","Artist":"Bodyjar","Album":null,"Url":null,"Time":"2:32"},{"TrackNumber":7,"Name":"You Say (Live)","Artist":"Bodyjar","Album":null,"Url":null,"Time":"4:08"},{"TrackNumber":8,"Name":"Sequel (Live)","Artist":"Bodyjar","Album":null,"Url":null,"Time":"2:35"},{"TrackNumber":9,"Name":"The Song Ramones the Same","Artist":"Bodyjar","Album":null,"Url":null,"Time":"1:59"}],"Name":"How It Works Bonus","Artist":"Bodyjar","Year":"2016","TotalLength":"26:12","Copyright":"(c) Mod Cons","MediumImageUri":"http://resources.wimpmusic.com/images/2d9e5d56/477c/4b0a/a002/9aaf3b103581/320x320.jpg","LargeImageUri":"http://resources.wimpmusic.com/images/2d9e5d56/477c/4b0a/a002/9aaf3b103581/1280x1280.jpg"}