{"ShortInfo":{"Id":"62567342","ImageUrl":"http://resources.wimpmusic.com/images/ed6a67f2/c68a/412e/ab33/dd95a23cca53/160x160.jpg","Url":"https://play.wimpmusic.com/album/62567342","Name":"Some Enchanted Evening (Live)","Artist":"Blue Öyster Cult"},"Tracks":[{"TrackNumber":1,"Name":"R.U. Ready 2 Rock (Live at Fox Theater, Atlanta, GA - April 1978)","Artist":"Blue Öyster Cult","Album":null,"Url":null,"Time":"6:07"},{"TrackNumber":2,"Name":"E.T.I.  (Extra Terrestrial Intelligence) (Live at Columbus Municipal Auditorium, Columbus, GA - April 1978)","Artist":"Blue Öyster Cult","Album":null,"Url":null,"Time":"5:18"},{"TrackNumber":3,"Name":"Astronomy (Live at Columbus Municipal Auditorium, Columbus, GA - April 1978)","Artist":"Blue Öyster Cult","Album":null,"Url":null,"Time":"8:25"},{"TrackNumber":4,"Name":"Kick out the Jams (Live at Fox Theater, Atlanta, GA - April 1978)","Artist":"Blue Öyster Cult","Album":null,"Url":null,"Time":"3:07"},{"TrackNumber":5,"Name":"Godzilla (Live at Newcastle City Hall, Newcastle, UK - June 1978)","Artist":"Blue Öyster Cult","Album":null,"Url":null,"Time":"4:13"},{"TrackNumber":6,"Name":"(Don't Fear) The Reaper (Live at Barton Coliseum, Little Rock, AR - April 1978)","Artist":"Blue Öyster Cult","Album":null,"Url":null,"Time":"6:10"},{"TrackNumber":7,"Name":"We Gotta Get out of This Place (Live at Newcastle City Hall, Newcastle, UK - June 1978)","Artist":"Blue Öyster Cult","Album":null,"Url":null,"Time":"4:39"}],"Name":"Some Enchanted Evening (Live)","Artist":"Blue Öyster Cult","Year":"2016","TotalLength":"37:48","Copyright":"(P) 1978 Columbia Records, a division of Sony Music Entertainment","MediumImageUri":"http://resources.wimpmusic.com/images/ed6a67f2/c68a/412e/ab33/dd95a23cca53/320x320.jpg","LargeImageUri":"http://resources.wimpmusic.com/images/ed6a67f2/c68a/412e/ab33/dd95a23cca53/1280x1280.jpg"}