{"ShortInfo":{"Id":"73203963","ImageUrl":"http://resources.wimpmusic.com/images/33d735d9/0277/40f4/b9b4/6f30fc84bb48/160x160.jpg","Url":"https://play.wimpmusic.com/album/73203963","Name":"Van Halen","Artist":"Van Halen"},"Tracks":[{"TrackNumber":1,"Name":"Runnin' With The Devil (2015 Remastered Version)","Artist":"Van Halen","Album":null,"Url":null,"Time":"3:35"},{"TrackNumber":2,"Name":"Eruption (2015 Remastered Version)","Artist":"Van Halen","Album":null,"Url":null,"Time":"1:41"},{"TrackNumber":3,"Name":"You Really Got Me (2015 Remastered Version)","Artist":"Van Halen","Album":null,"Url":null,"Time":"2:36"},{"TrackNumber":4,"Name":"Ain't Talkin' 'Bout Love (2015 Remastered Version)","Artist":"Van Halen","Album":null,"Url":null,"Time":"3:47"},{"TrackNumber":5,"Name":"I'm The One (2015 Remastered Version)","Artist":"Van Halen","Album":null,"Url":null,"Time":"3:44"},{"TrackNumber":6,"Name":"Jamie's Cryin' (2015 Remastered Version)","Artist":"Van Halen","Album":null,"Url":null,"Time":"3:29"},{"TrackNumber":7,"Name":"Atomic Punk (2015 Remastered Version)","Artist":"Van Halen","Album":null,"Url":null,"Time":"3:00"},{"TrackNumber":8,"Name":"Feel Your Love Tonight (2015 Remastered Version)","Artist":"Van Halen","Album":null,"Url":null,"Time":"3:40"},{"TrackNumber":9,"Name":"Little Dreamer (2015 Remastered Version)","Artist":"Van Halen","Album":null,"Url":null,"Time":"3:22"},{"TrackNumber":10,"Name":"Ice Cream Man (2015 Remastered Version)","Artist":"Van Halen","Album":null,"Url":null,"Time":"3:17"},{"TrackNumber":11,"Name":"On Fire (2015 Remastered Version)","Artist":"Van Halen","Album":null,"Url":null,"Time":"3:00"}],"Name":"Van Halen","Artist":"Van Halen","Year":"1990","TotalLength":"35:13","Copyright":"1978 Warner Bros. Records.","MediumImageUri":"http://resources.wimpmusic.com/images/33d735d9/0277/40f4/b9b4/6f30fc84bb48/320x320.jpg","LargeImageUri":"http://resources.wimpmusic.com/images/33d735d9/0277/40f4/b9b4/6f30fc84bb48/1280x1280.jpg"}