{"ShortInfo":{"Id":"91639758","ImageUrl":"http://resources.wimpmusic.com/images/abdd72b8/9c33/4d49/8f3b/4dd8abdf9608/160x160.jpg","Url":"https://play.wimpmusic.com/album/91639758","Name":"Live Broadcast - 12th May 1989 Veterans Memorial Coliseum","Artist":"Heart"},"Tracks":[{"TrackNumber":1,"Name":"Bad Animals (Broadcast 1989)","Artist":"Heart","Album":null,"Url":null,"Time":"10:27"},{"TrackNumber":2,"Name":"The Wolf (Broadcast 1989)","Artist":"Heart","Album":null,"Url":null,"Time":"5:21"},{"TrackNumber":3,"Name":"Barracuda (Broadcast 1989)","Artist":"Heart","Album":null,"Url":null,"Time":"4:19"},{"TrackNumber":4,"Name":"Nothing At All (Broadcast 1989)","Artist":"Heart","Album":null,"Url":null,"Time":"5:09"},{"TrackNumber":5,"Name":"What About Love (Broadcast 1989)","Artist":"Heart","Album":null,"Url":null,"Time":"4:30"},{"TrackNumber":6,"Name":"Dreamboat Annie (Broadcast 1989)","Artist":"Heart","Album":null,"Url":null,"Time":"4:18"},{"TrackNumber":7,"Name":"These Dreams (Broadcast 1989)","Artist":"Heart","Album":null,"Url":null,"Time":"4:39"},{"TrackNumber":8,"Name":"Straight On (Broadcast 1989)","Artist":"Heart","Album":null,"Url":null,"Time":"3:58"},{"TrackNumber":9,"Name":"Who Will You Run To (Broadcast 1989)","Artist":"Heart","Album":null,"Url":null,"Time":"4:50"},{"TrackNumber":10,"Name":"Never (Broadcast 1989)","Artist":"Heart","Album":null,"Url":null,"Time":"4:17"},{"TrackNumber":11,"Name":"How Can I Refuse (Broadcast 1989)","Artist":"Heart","Album":null,"Url":null,"Time":"4:55"},{"TrackNumber":12,"Name":"Crazy On You (Broadcast 1989)","Artist":"Heart","Album":null,"Url":null,"Time":"4:20"},{"TrackNumber":13,"Name":"If Looks Could Kill (Broadcast 1989)","Artist":"Heart","Album":null,"Url":null,"Time":"5:10"},{"TrackNumber":14,"Name":"Bebe le Strange (Broadcast 1989)","Artist":"Heart","Album":null,"Url":null,"Time":"3:23"},{"TrackNumber":15,"Name":"Alone (Broadcast 1989)","Artist":"Heart","Album":null,"Url":null,"Time":"3:47"},{"TrackNumber":16,"Name":"Keep A Knockin' / Rock And Roll (Broadcast 1989)","Artist":"Heart","Album":null,"Url":null,"Time":"5:36"}],"Name":"Live Broadcast - 12th May 1989 Veterans Memorial Coliseum","Artist":"Heart","Year":"2018","TotalLength":"1:18:59","Copyright":"Denny Carmassi, Howard M Leese, Mark Andes, Ann Wilson (Dustin), Susan L Ennis, Roger Douglas Fisher,  Nancy Wilson (Lamoureaux), Micheal Joseph Derosier, Mark Clifford Mueller, Sharon Elaine Alton,  Brian Raymond Allen, James Douglas Vallance, Diane Eve Warren, David Bruce Cassidy, John Kenneth Wetton, Sue Shifrin, Jack Conrad, Bob A Garrett, Tom Kelly, Billy Steinberg, Richard W Penniman, Robert Plant, John Bonham, John Paul Jones, Jimmy Page","MediumImageUri":"http://resources.wimpmusic.com/images/abdd72b8/9c33/4d49/8f3b/4dd8abdf9608/320x320.jpg","LargeImageUri":"http://resources.wimpmusic.com/images/abdd72b8/9c33/4d49/8f3b/4dd8abdf9608/1280x1280.jpg"}