{"ShortInfo":{"Id":"94414411","ImageUrl":"http://resources.wimpmusic.com/images/d96d9271/8263/4c14/8e12/345830dfdc6f/160x160.jpg","Url":"https://play.wimpmusic.com/album/94414411","Name":"Legendary Hits","Artist":"The Allman Brothers Band"},"Tracks":[{"TrackNumber":1,"Name":"Midnight Rider","Artist":"The Allman Brothers Band","Album":null,"Url":null,"Time":"2:55"},{"TrackNumber":2,"Name":"Whipping Post","Artist":"The Allman Brothers Band","Album":null,"Url":null,"Time":"5:19"},{"TrackNumber":3,"Name":"Little Martha","Artist":"The Allman Brothers Band","Album":null,"Url":null,"Time":"2:07"},{"TrackNumber":4,"Name":"Hoochie Coochie Man","Artist":"The Allman Brothers Band","Album":null,"Url":null,"Time":"4:54"},{"TrackNumber":5,"Name":"Wasted Words","Artist":"The Allman Brothers Band","Album":null,"Url":null,"Time":"4:16"},{"TrackNumber":6,"Name":"Statesboro Blues (Live At The Fillmore East)","Artist":"The Allman Brothers Band","Album":null,"Url":null,"Time":"4:17"},{"TrackNumber":7,"Name":"Jessica","Artist":"The Allman Brothers Band","Album":null,"Url":null,"Time":"7:27"},{"TrackNumber":8,"Name":"Win, Lose Or Draw","Artist":"The Allman Brothers Band","Album":null,"Url":null,"Time":"4:44"},{"TrackNumber":9,"Name":"Revival","Artist":"The Allman Brothers Band","Album":null,"Url":null,"Time":"4:03"},{"TrackNumber":10,"Name":"Trouble No More (Live At The Fillmore East)","Artist":"The Allman Brothers Band","Album":null,"Url":null,"Time":"3:46"},{"TrackNumber":11,"Name":"Hot 'Lanta (Live At The Fillmore East)","Artist":"The Allman Brothers Band","Album":null,"Url":null,"Time":"5:19"},{"TrackNumber":12,"Name":"Stormy Monday","Artist":"The Allman Brothers Band","Album":null,"Url":null,"Time":"8:47"}],"Name":"Legendary Hits","Artist":"The Allman Brothers Band","Year":"1995","TotalLength":"57:37","Copyright":"© 1995 UMG Recordings, Inc.","MediumImageUri":"http://resources.wimpmusic.com/images/d96d9271/8263/4c14/8e12/345830dfdc6f/320x320.jpg","LargeImageUri":"http://resources.wimpmusic.com/images/d96d9271/8263/4c14/8e12/345830dfdc6f/1280x1280.jpg"}